{
  "name" : null,
  "per_page" : 30,
  "page" : 1,
  "total_results" : 1,
  "results" : [ {
    "min_species_ancestry" : null,
    "iconic_taxon_name" : "Aves",
    "created_at" : null,
    "iconic_taxon_id" : 3,
    "atlas_id" : null,
    "name" : "Urocissa erythroryncha",
    "complete_species_count" : null,
    "default_photo" : {
      "url" : "https://farm5.staticflickr.com/4003/4360887073_eb8801fe2d_s.jpg",
      "license_code" : "cc-by-sa",
      "type" : null,
      "attribution" : "(c) Charles Lam, some rights reserved (CC BY-SA)",
      "native_photo_id" : null,
      "small_url" : null,
      "medium_url" : "https://farm5.staticflickr.com/4003/4360887073_eb8801fe2d.jpg",
      "large_url" : null,
      "square_url" : "https://farm5.staticflickr.com/4003/4360887073_eb8801fe2d_s.jpg",
      "original_url" : null,
      "native_page_url" : null,
      "id" : 72711,
      "flags" : [ ],
      "original_dimensions" : null
    },
    "rank" : "species",
    "ancestry" : "48460/1/2/355675/3/7251/7823/8413",
    "rank_level" : 10,
    "taxon_schemes_count" : 2,
    "ancestor_ids" : [ 48460, 1, 2, 355675, 3, 7251, 7823, 8413 ],
    "id" : 495200,
    "parent_id" : 8413,
    "taxon_changes_count" : 1,
    "preferred_common_name" : "Red-billed Blue-Magpie",
    "extinct" : false,
    "is_active" : true,
    "observations_count" : 64,
    "taxon_photos" : [ {
      "photo" : {
        "url" : "https://farm5.staticflickr.com/4003/4360887073_eb8801fe2d_s.jpg",
        "license_code" : "cc-by-sa",
        "type" : "FlickrPhoto",
        "attribution" : "(c) Charles Lam, some rights reserved (CC BY-SA)",
        "native_photo_id" : "4360887073",
        "small_url" : "https://farm5.staticflickr.com/4003/4360887073_eb8801fe2d_m.jpg",
        "medium_url" : "https://farm5.staticflickr.com/4003/4360887073_eb8801fe2d.jpg",
        "large_url" : "https://farm5.staticflickr.com/4003/4360887073_eb8801fe2d_b.jpg",
        "square_url" : "https://farm5.staticflickr.com/4003/4360887073_eb8801fe2d_s.jpg",
        "original_url" : "https://farm5.staticflickr.com/4003/4360887073_eb8801fe2d_b.jpg",
        "native_page_url" : "http://www.flickr.com/photos/49296659@N00/4360887073",
        "id" : 72711,
        "flags" : [ ],
        "original_dimensions" : null
      },
      "taxon" : {
        "min_species_ancestry" : "48460,1,2,355675,3,7251,7823,8413,495200",
        "iconic_taxon_name" : "Aves",
        "created_at" : "2016-05-13T22:03:03+00:00",
        "iconic_taxon_id" : 3,
        "atlas_id" : null,
        "name" : "Urocissa erythroryncha",
        "complete_species_count" : null,
        "default_photo" : {
          "url" : "https://farm5.staticflickr.com/4003/4360887073_eb8801fe2d_s.jpg",
          "license_code" : "cc-by-sa",
          "type" : null,
          "attribution" : "(c) Charles Lam, some rights reserved (CC BY-SA)",
          "native_photo_id" : null,
          "small_url" : null,
          "medium_url" : "https://farm5.staticflickr.com/4003/4360887073_eb8801fe2d.jpg",
          "large_url" : null,
          "square_url" : "https://farm5.staticflickr.com/4003/4360887073_eb8801fe2d_s.jpg",
          "original_url" : null,
          "native_page_url" : null,
          "id" : 72711,
          "flags" : [ ],
          "original_dimensions" : null
        },
        "rank" : "species",
        "ancestry" : "48460/1/2/355675/3/7251/7823/8413",
        "rank_level" : 10,
        "taxon_schemes_count" : 2,
        "ancestor_ids" : [ 48460, 1, 2, 355675, 3, 7251, 7823, 8413, 495200 ],
        "id" : 495200,
        "parent_id" : 8413,
        "taxon_changes_count" : 1,
        "preferred_common_name" : "Red-billed Blue-Magpie",
        "extinct" : false,
        "is_active" : true,
        "observations_count" : 64,
        "taxon_photos" : null,
        "conservation_statuses" : null,
        "children" : null,
        "ancestors" : null,
        "wikipedia_summary" : null
      }
    }, {
      "photo" : {
        "url" : "https://farm1.staticflickr.com/137/326162704_45131271c6_s.jpg",
        "license_code" : "cc-by-nc",
        "type" : "FlickrPhoto",
        "attribution" : "(c) Davis Kwan, some rights reserved (CC BY-NC)",
        "native_photo_id" : "326162704",
        "small_url" : "https://farm1.staticflickr.com/137/326162704_45131271c6_m.jpg",
        "medium_url" : "https://farm1.staticflickr.com/137/326162704_45131271c6.jpg",
        "large_url" : "https://farm1.staticflickr.com/137/326162704_45131271c6_b.jpg",
        "square_url" : "https://farm1.staticflickr.com/137/326162704_45131271c6_s.jpg",
        "original_url" : "https://farm1.staticflickr.com/137/326162704_45131271c6_o.jpg",
        "native_page_url" : "http://www.flickr.com/photos/kwingkai/326162704/",
        "id" : 553712,
        "flags" : [ ],
        "original_dimensions" : null
      },
      "taxon" : {
        "min_species_ancestry" : "48460,1,2,355675,3,7251,7823,8413,495200",
        "iconic_taxon_name" : "Aves",
        "created_at" : "2016-05-13T22:03:03+00:00",
        "iconic_taxon_id" : 3,
        "atlas_id" : null,
        "name" : "Urocissa erythroryncha",
        "complete_species_count" : null,
        "default_photo" : {
          "url" : "https://farm5.staticflickr.com/4003/4360887073_eb8801fe2d_s.jpg",
          "license_code" : "cc-by-sa",
          "type" : null,
          "attribution" : "(c) Charles Lam, some rights reserved (CC BY-SA)",
          "native_photo_id" : null,
          "small_url" : null,
          "medium_url" : "https://farm5.staticflickr.com/4003/4360887073_eb8801fe2d.jpg",
          "large_url" : null,
          "square_url" : "https://farm5.staticflickr.com/4003/4360887073_eb8801fe2d_s.jpg",
          "original_url" : null,
          "native_page_url" : null,
          "id" : 72711,
          "flags" : [ ],
          "original_dimensions" : null
        },
        "rank" : "species",
        "ancestry" : "48460/1/2/355675/3/7251/7823/8413",
        "rank_level" : 10,
        "taxon_schemes_count" : 2,
        "ancestor_ids" : [ 48460, 1, 2, 355675, 3, 7251, 7823, 8413, 495200 ],
        "id" : 495200,
        "parent_id" : 8413,
        "taxon_changes_count" : 1,
        "preferred_common_name" : "Red-billed Blue-Magpie",
        "extinct" : false,
        "is_active" : true,
        "observations_count" : 64,
        "taxon_photos" : null,
        "conservation_statuses" : null,
        "children" : null,
        "ancestors" : null,
        "wikipedia_summary" : null
      }
    }, {
      "photo" : {
        "url" : "https://farm4.staticflickr.com/3351/3307077639_4480d088ff_s.jpg",
        "license_code" : "cc-by-sa",
        "type" : "FlickrPhoto",
        "attribution" : "(c) Charles Lam, some rights reserved (CC BY-SA)",
        "native_photo_id" : "3307077639",
        "small_url" : "https://farm4.staticflickr.com/3351/3307077639_4480d088ff_m.jpg",
        "medium_url" : "https://farm4.staticflickr.com/3351/3307077639_4480d088ff.jpg",
        "large_url" : "https://farm4.staticflickr.com/3351/3307077639_4480d088ff_b.jpg",
        "square_url" : "https://farm4.staticflickr.com/3351/3307077639_4480d088ff_s.jpg",
        "original_url" : "https://farm4.staticflickr.com/3351/3307077639_94c4dfe7dd_o.jpg",
        "native_page_url" : "http://www.flickr.com/photos/kclama/3307077639/",
        "id" : 553713,
        "flags" : [ ],
        "original_dimensions" : null
      },
      "taxon" : {
        "min_species_ancestry" : "48460,1,2,355675,3,7251,7823,8413,495200",
        "iconic_taxon_name" : "Aves",
        "created_at" : "2016-05-13T22:03:03+00:00",
        "iconic_taxon_id" : 3,
        "atlas_id" : null,
        "name" : "Urocissa erythroryncha",
        "complete_species_count" : null,
        "default_photo" : {
          "url" : "https://farm5.staticflickr.com/4003/4360887073_eb8801fe2d_s.jpg",
          "license_code" : "cc-by-sa",
          "type" : null,
          "attribution" : "(c) Charles Lam, some rights reserved (CC BY-SA)",
          "native_photo_id" : null,
          "small_url" : null,
          "medium_url" : "https://farm5.staticflickr.com/4003/4360887073_eb8801fe2d.jpg",
          "large_url" : null,
          "square_url" : "https://farm5.staticflickr.com/4003/4360887073_eb8801fe2d_s.jpg",
          "original_url" : null,
          "native_page_url" : null,
          "id" : 72711,
          "flags" : [ ],
          "original_dimensions" : null
        },
        "rank" : "species",
        "ancestry" : "48460/1/2/355675/3/7251/7823/8413",
        "rank_level" : 10,
        "taxon_schemes_count" : 2,
        "ancestor_ids" : [ 48460, 1, 2, 355675, 3, 7251, 7823, 8413, 495200 ],
        "id" : 495200,
        "parent_id" : 8413,
        "taxon_changes_count" : 1,
        "preferred_common_name" : "Red-billed Blue-Magpie",
        "extinct" : false,
        "is_active" : true,
        "observations_count" : 64,
        "taxon_photos" : null,
        "conservation_statuses" : null,
        "children" : null,
        "ancestors" : null,
        "wikipedia_summary" : null
      }
    }, {
      "photo" : {
        "url" : "https://farm4.staticflickr.com/3376/3413399810_e51e99bca6_s.jpg",
        "license_code" : "cc-by-sa",
        "type" : "FlickrPhoto",
        "attribution" : "(c) Charles Lam, some rights reserved (CC BY-SA)",
        "native_photo_id" : "3413399810",
        "small_url" : "https://farm4.staticflickr.com/3376/3413399810_e51e99bca6_m.jpg",
        "medium_url" : "https://farm4.staticflickr.com/3376/3413399810_e51e99bca6.jpg",
        "large_url" : "https://farm4.staticflickr.com/3376/3413399810_e51e99bca6_b.jpg",
        "square_url" : "https://farm4.staticflickr.com/3376/3413399810_e51e99bca6_s.jpg",
        "original_url" : "https://farm4.staticflickr.com/3376/3413399810_d9e1e5efeb_o.jpg",
        "native_page_url" : "http://www.flickr.com/photos/kclama/3413399810/",
        "id" : 553714,
        "flags" : [ ],
        "original_dimensions" : null
      },
      "taxon" : {
        "min_species_ancestry" : "48460,1,2,355675,3,7251,7823,8413,495200",
        "iconic_taxon_name" : "Aves",
        "created_at" : "2016-05-13T22:03:03+00:00",
        "iconic_taxon_id" : 3,
        "atlas_id" : null,
        "name" : "Urocissa erythroryncha",
        "complete_species_count" : null,
        "default_photo" : {
          "url" : "https://farm5.staticflickr.com/4003/4360887073_eb8801fe2d_s.jpg",
          "license_code" : "cc-by-sa",
          "type" : null,
          "attribution" : "(c) Charles Lam, some rights reserved (CC BY-SA)",
          "native_photo_id" : null,
          "small_url" : null,
          "medium_url" : "https://farm5.staticflickr.com/4003/4360887073_eb8801fe2d.jpg",
          "large_url" : null,
          "square_url" : "https://farm5.staticflickr.com/4003/4360887073_eb8801fe2d_s.jpg",
          "original_url" : null,
          "native_page_url" : null,
          "id" : 72711,
          "flags" : [ ],
          "original_dimensions" : null
        },
        "rank" : "species",
        "ancestry" : "48460/1/2/355675/3/7251/7823/8413",
        "rank_level" : 10,
        "taxon_schemes_count" : 2,
        "ancestor_ids" : [ 48460, 1, 2, 355675, 3, 7251, 7823, 8413, 495200 ],
        "id" : 495200,
        "parent_id" : 8413,
        "taxon_changes_count" : 1,
        "preferred_common_name" : "Red-billed Blue-Magpie",
        "extinct" : false,
        "is_active" : true,
        "observations_count" : 64,
        "taxon_photos" : null,
        "conservation_statuses" : null,
        "children" : null,
        "ancestors" : null,
        "wikipedia_summary" : null
      }
    }, {
      "photo" : {
        "url" : "https://static.inaturalist.org/photos/152312/square.jpg?1444546955",
        "license_code" : "cc-by-nc-nd",
        "type" : "LocalPhoto",
        "attribution" : "(c) Allan Hopkins, some rights reserved (CC BY-NC-ND)",
        "native_photo_id" : "7183859837",
        "small_url" : "https://static.inaturalist.org/photos/152312/small.jpg?1444546955",
        "medium_url" : "https://static.inaturalist.org/photos/152312/medium.jpg?1444546955",
        "large_url" : "https://static.inaturalist.org/photos/152312/large.jpg?1444546955",
        "square_url" : "https://static.inaturalist.org/photos/152312/square.jpg?1444546955",
        "original_url" : "https://static.inaturalist.org/photos/152312/original.jpg?1444546955",
        "native_page_url" : "http://www.flickr.com/photos/44096805@N07/7183859837",
        "id" : 152312,
        "flags" : [ ],
        "original_dimensions" : {
          "width" : 1260,
          "height" : 900
        }
      },
      "taxon" : {
        "min_species_ancestry" : "48460,1,2,355675,3,7251,7823,8413,495200",
        "iconic_taxon_name" : "Aves",
        "created_at" : "2016-05-13T22:03:03+00:00",
        "iconic_taxon_id" : 3,
        "atlas_id" : null,
        "name" : "Urocissa erythroryncha",
        "complete_species_count" : null,
        "default_photo" : {
          "url" : "https://farm5.staticflickr.com/4003/4360887073_eb8801fe2d_s.jpg",
          "license_code" : "cc-by-sa",
          "type" : null,
          "attribution" : "(c) Charles Lam, some rights reserved (CC BY-SA)",
          "native_photo_id" : null,
          "small_url" : null,
          "medium_url" : "https://farm5.staticflickr.com/4003/4360887073_eb8801fe2d.jpg",
          "large_url" : null,
          "square_url" : "https://farm5.staticflickr.com/4003/4360887073_eb8801fe2d_s.jpg",
          "original_url" : null,
          "native_page_url" : null,
          "id" : 72711,
          "flags" : [ ],
          "original_dimensions" : null
        },
        "rank" : "species",
        "ancestry" : "48460/1/2/355675/3/7251/7823/8413",
        "rank_level" : 10,
        "taxon_schemes_count" : 2,
        "ancestor_ids" : [ 48460, 1, 2, 355675, 3, 7251, 7823, 8413, 495200 ],
        "id" : 495200,
        "parent_id" : 8413,
        "taxon_changes_count" : 1,
        "preferred_common_name" : "Red-billed Blue-Magpie",
        "extinct" : false,
        "is_active" : true,
        "observations_count" : 64,
        "taxon_photos" : null,
        "conservation_statuses" : null,
        "children" : null,
        "ancestors" : null,
        "wikipedia_summary" : null
      }
    }, {
      "photo" : {
        "url" : "https://farm1.staticflickr.com/31/58952737_695c62dee4_s.jpg",
        "license_code" : "cc-by-sa",
        "type" : "FlickrPhoto",
        "attribution" : "(c) Charles Lam, some rights reserved (CC BY-SA)",
        "native_photo_id" : "58952737",
        "small_url" : "https://farm1.staticflickr.com/31/58952737_695c62dee4_m.jpg",
        "medium_url" : "https://farm1.staticflickr.com/31/58952737_695c62dee4.jpg",
        "large_url" : "https://farm1.staticflickr.com/31/58952737_695c62dee4.jpg",
        "square_url" : "https://farm1.staticflickr.com/31/58952737_695c62dee4_s.jpg",
        "original_url" : "https://farm1.staticflickr.com/31/58952737_695c62dee4_o.jpg",
        "native_page_url" : "https://www.flickr.com/photos/kclama/58952737/",
        "id" : 1629673,
        "flags" : [ ],
        "original_dimensions" : null
      },
      "taxon" : {
        "min_species_ancestry" : "48460,1,2,355675,3,7251,7823,8413,495200",
        "iconic_taxon_name" : "Aves",
        "created_at" : "2016-05-13T22:03:03+00:00",
        "iconic_taxon_id" : 3,
        "atlas_id" : null,
        "name" : "Urocissa erythroryncha",
        "complete_species_count" : null,
        "default_photo" : {
          "url" : "https://farm5.staticflickr.com/4003/4360887073_eb8801fe2d_s.jpg",
          "license_code" : "cc-by-sa",
          "type" : null,
          "attribution" : "(c) Charles Lam, some rights reserved (CC BY-SA)",
          "native_photo_id" : null,
          "small_url" : null,
          "medium_url" : "https://farm5.staticflickr.com/4003/4360887073_eb8801fe2d.jpg",
          "large_url" : null,
          "square_url" : "https://farm5.staticflickr.com/4003/4360887073_eb8801fe2d_s.jpg",
          "original_url" : null,
          "native_page_url" : null,
          "id" : 72711,
          "flags" : [ ],
          "original_dimensions" : null
        },
        "rank" : "species",
        "ancestry" : "48460/1/2/355675/3/7251/7823/8413",
        "rank_level" : 10,
        "taxon_schemes_count" : 2,
        "ancestor_ids" : [ 48460, 1, 2, 355675, 3, 7251, 7823, 8413, 495200 ],
        "id" : 495200,
        "parent_id" : 8413,
        "taxon_changes_count" : 1,
        "preferred_common_name" : "Red-billed Blue-Magpie",
        "extinct" : false,
        "is_active" : true,
        "observations_count" : 64,
        "taxon_photos" : null,
        "conservation_statuses" : null,
        "children" : null,
        "ancestors" : null,
        "wikipedia_summary" : null
      }
    }, {
      "photo" : {
        "url" : "https://farm8.staticflickr.com/7281/16789002642_1c69e29e81_s.jpg",
        "license_code" : "cc-by-nc",
        "type" : "FlickrPhoto",
        "attribution" : "(c) David Cook, some rights reserved (CC BY-NC)",
        "native_photo_id" : "16789002642",
        "small_url" : "https://farm8.staticflickr.com/7281/16789002642_1c69e29e81_m.jpg",
        "medium_url" : "https://farm8.staticflickr.com/7281/16789002642_1c69e29e81.jpg",
        "large_url" : "https://farm8.staticflickr.com/7281/16789002642_1c69e29e81_b.jpg",
        "square_url" : "https://farm8.staticflickr.com/7281/16789002642_1c69e29e81_s.jpg",
        "original_url" : "https://farm8.staticflickr.com/7281/16789002642_45b1b9f677_o.jpg",
        "native_page_url" : "https://www.flickr.com/photos/kookr/16789002642/",
        "id" : 1629674,
        "flags" : [ ],
        "original_dimensions" : null
      },
      "taxon" : {
        "min_species_ancestry" : "48460,1,2,355675,3,7251,7823,8413,495200",
        "iconic_taxon_name" : "Aves",
        "created_at" : "2016-05-13T22:03:03+00:00",
        "iconic_taxon_id" : 3,
        "atlas_id" : null,
        "name" : "Urocissa erythroryncha",
        "complete_species_count" : null,
        "default_photo" : {
          "url" : "https://farm5.staticflickr.com/4003/4360887073_eb8801fe2d_s.jpg",
          "license_code" : "cc-by-sa",
          "type" : null,
          "attribution" : "(c) Charles Lam, some rights reserved (CC BY-SA)",
          "native_photo_id" : null,
          "small_url" : null,
          "medium_url" : "https://farm5.staticflickr.com/4003/4360887073_eb8801fe2d.jpg",
          "large_url" : null,
          "square_url" : "https://farm5.staticflickr.com/4003/4360887073_eb8801fe2d_s.jpg",
          "original_url" : null,
          "native_page_url" : null,
          "id" : 72711,
          "flags" : [ ],
          "original_dimensions" : null
        },
        "rank" : "species",
        "ancestry" : "48460/1/2/355675/3/7251/7823/8413",
        "rank_level" : 10,
        "taxon_schemes_count" : 2,
        "ancestor_ids" : [ 48460, 1, 2, 355675, 3, 7251, 7823, 8413, 495200 ],
        "id" : 495200,
        "parent_id" : 8413,
        "taxon_changes_count" : 1,
        "preferred_common_name" : "Red-billed Blue-Magpie",
        "extinct" : false,
        "is_active" : true,
        "observations_count" : 64,
        "taxon_photos" : null,
        "conservation_statuses" : null,
        "children" : null,
        "ancestors" : null,
        "wikipedia_summary" : null
      }
    }, {
      "photo" : {
        "url" : "https://farm6.staticflickr.com/5294/5416211849_34f7271539_s.jpg",
        "license_code" : "cc-by-nc-sa",
        "type" : "FlickrPhoto",
        "attribution" : "(c) bob|P-&-S, some rights reserved (CC BY-NC-SA)",
        "native_photo_id" : "5416211849",
        "small_url" : "https://farm6.staticflickr.com/5294/5416211849_34f7271539_m.jpg",
        "medium_url" : "https://farm6.staticflickr.com/5294/5416211849_34f7271539.jpg",
        "large_url" : "https://farm6.staticflickr.com/5294/5416211849_34f7271539_b.jpg",
        "square_url" : "https://farm6.staticflickr.com/5294/5416211849_34f7271539_s.jpg",
        "original_url" : "https://farm6.staticflickr.com/5294/5416211849_1e2564bc93_o.jpg",
        "native_page_url" : "https://www.flickr.com/photos/mahbobyusof/5416211849/",
        "id" : 1629675,
        "flags" : [ ],
        "original_dimensions" : null
      },
      "taxon" : {
        "min_species_ancestry" : "48460,1,2,355675,3,7251,7823,8413,495200",
        "iconic_taxon_name" : "Aves",
        "created_at" : "2016-05-13T22:03:03+00:00",
        "iconic_taxon_id" : 3,
        "atlas_id" : null,
        "name" : "Urocissa erythroryncha",
        "complete_species_count" : null,
        "default_photo" : {
          "url" : "https://farm5.staticflickr.com/4003/4360887073_eb8801fe2d_s.jpg",
          "license_code" : "cc-by-sa",
          "type" : null,
          "attribution" : "(c) Charles Lam, some rights reserved (CC BY-SA)",
          "native_photo_id" : null,
          "small_url" : null,
          "medium_url" : "https://farm5.staticflickr.com/4003/4360887073_eb8801fe2d.jpg",
          "large_url" : null,
          "square_url" : "https://farm5.staticflickr.com/4003/4360887073_eb8801fe2d_s.jpg",
          "original_url" : null,
          "native_page_url" : null,
          "id" : 72711,
          "flags" : [ ],
          "original_dimensions" : null
        },
        "rank" : "species",
        "ancestry" : "48460/1/2/355675/3/7251/7823/8413",
        "rank_level" : 10,
        "taxon_schemes_count" : 2,
        "ancestor_ids" : [ 48460, 1, 2, 355675, 3, 7251, 7823, 8413, 495200 ],
        "id" : 495200,
        "parent_id" : 8413,
        "taxon_changes_count" : 1,
        "preferred_common_name" : "Red-billed Blue-Magpie",
        "extinct" : false,
        "is_active" : true,
        "observations_count" : 64,
        "taxon_photos" : null,
        "conservation_statuses" : null,
        "children" : null,
        "ancestors" : null,
        "wikipedia_summary" : null
      }
    }, {
      "photo" : {
        "url" : "https://farm4.staticflickr.com/3693/9960247503_4a6922ee38_s.jpg",
        "license_code" : "cc-by-sa",
        "type" : "FlickrPhoto",
        "attribution" : "(c) Charles Lam, some rights reserved (CC BY-SA)",
        "native_photo_id" : "9960247503",
        "small_url" : "https://farm4.staticflickr.com/3693/9960247503_4a6922ee38_m.jpg",
        "medium_url" : "https://farm4.staticflickr.com/3693/9960247503_4a6922ee38.jpg",
        "large_url" : "https://farm4.staticflickr.com/3693/9960247503_4a6922ee38_b.jpg",
        "square_url" : "https://farm4.staticflickr.com/3693/9960247503_4a6922ee38_s.jpg",
        "original_url" : "https://farm4.staticflickr.com/3693/9960247503_0407b60d51_o.jpg",
        "native_page_url" : "https://www.flickr.com/photos/kclama/9960247503/",
        "id" : 1629676,
        "flags" : [ ],
        "original_dimensions" : null
      },
      "taxon" : {
        "min_species_ancestry" : "48460,1,2,355675,3,7251,7823,8413,495200",
        "iconic_taxon_name" : "Aves",
        "created_at" : "2016-05-13T22:03:03+00:00",
        "iconic_taxon_id" : 3,
        "atlas_id" : null,
        "name" : "Urocissa erythroryncha",
        "complete_species_count" : null,
        "default_photo" : {
          "url" : "https://farm5.staticflickr.com/4003/4360887073_eb8801fe2d_s.jpg",
          "license_code" : "cc-by-sa",
          "type" : null,
          "attribution" : "(c) Charles Lam, some rights reserved (CC BY-SA)",
          "native_photo_id" : null,
          "small_url" : null,
          "medium_url" : "https://farm5.staticflickr.com/4003/4360887073_eb8801fe2d.jpg",
          "large_url" : null,
          "square_url" : "https://farm5.staticflickr.com/4003/4360887073_eb8801fe2d_s.jpg",
          "original_url" : null,
          "native_page_url" : null,
          "id" : 72711,
          "flags" : [ ],
          "original_dimensions" : null
        },
        "rank" : "species",
        "ancestry" : "48460/1/2/355675/3/7251/7823/8413",
        "rank_level" : 10,
        "taxon_schemes_count" : 2,
        "ancestor_ids" : [ 48460, 1, 2, 355675, 3, 7251, 7823, 8413, 495200 ],
        "id" : 495200,
        "parent_id" : 8413,
        "taxon_changes_count" : 1,
        "preferred_common_name" : "Red-billed Blue-Magpie",
        "extinct" : false,
        "is_active" : true,
        "observations_count" : 64,
        "taxon_photos" : null,
        "conservation_statuses" : null,
        "children" : null,
        "ancestors" : null,
        "wikipedia_summary" : null
      }
    } ],
    "conservation_statuses" : [ {
      "description" : null,
      "iucn" : 10,
      "url" : "http://www.iucnredlist.org/details/106005730",
      "authority" : "IUCN Red List",
      "taxon_id" : 495200,
      "place" : null,
      "status" : "LC"
    } ],
    "children" : [ {
      "min_species_ancestry" : null,
      "iconic_taxon_name" : "Aves",
      "created_at" : null,
      "iconic_taxon_id" : 3,
      "atlas_id" : null,
      "name" : "Urocissa erythroryncha alticola",
      "complete_species_count" : null,
      "default_photo" : null,
      "rank" : "subspecies",
      "ancestry" : "48460/1/2/355675/3/7251/7823/8413/495200",
      "rank_level" : 5,
      "taxon_schemes_count" : 1,
      "ancestor_ids" : [ 48460, 1, 2, 355675, 3, 7251, 7823, 8413, 495200, 495195 ],
      "id" : 495195,
      "parent_id" : 495200,
      "taxon_changes_count" : 0,
      "preferred_common_name" : null,
      "extinct" : null,
      "is_active" : true,
      "observations_count" : 0,
      "taxon_photos" : null,
      "conservation_statuses" : null,
      "children" : null,
      "ancestors" : null,
      "wikipedia_summary" : null
    }, {
      "min_species_ancestry" : null,
      "iconic_taxon_name" : "Aves",
      "created_at" : null,
      "iconic_taxon_id" : 3,
      "atlas_id" : null,
      "name" : "Urocissa erythroryncha brevivexilla",
      "complete_species_count" : null,
      "default_photo" : null,
      "rank" : "subspecies",
      "ancestry" : "48460/1/2/355675/3/7251/7823/8413/495200",
      "rank_level" : 5,
      "taxon_schemes_count" : 1,
      "ancestor_ids" : [ 48460, 1, 2, 355675, 3, 7251, 7823, 8413, 495200, 495196 ],
      "id" : 495196,
      "parent_id" : 495200,
      "taxon_changes_count" : 0,
      "preferred_common_name" : null,
      "extinct" : null,
      "is_active" : true,
      "observations_count" : 0,
      "taxon_photos" : null,
      "conservation_statuses" : null,
      "children" : null,
      "ancestors" : null,
      "wikipedia_summary" : null
    }, {
      "min_species_ancestry" : null,
      "iconic_taxon_name" : "Aves",
      "created_at" : null,
      "iconic_taxon_id" : 3,
      "atlas_id" : null,
      "name" : "Urocissa erythroryncha erythroryncha",
      "complete_species_count" : null,
      "default_photo" : null,
      "rank" : "subspecies",
      "ancestry" : "48460/1/2/355675/3/7251/7823/8413/495200",
      "rank_level" : 5,
      "taxon_schemes_count" : 1,
      "ancestor_ids" : [ 48460, 1, 2, 355675, 3, 7251, 7823, 8413, 495200, 495197 ],
      "id" : 495197,
      "parent_id" : 495200,
      "taxon_changes_count" : 0,
      "preferred_common_name" : null,
      "extinct" : null,
      "is_active" : true,
      "observations_count" : 0,
      "taxon_photos" : null,
      "conservation_statuses" : null,
      "children" : null,
      "ancestors" : null,
      "wikipedia_summary" : null
    }, {
      "min_species_ancestry" : null,
      "iconic_taxon_name" : "Aves",
      "created_at" : null,
      "iconic_taxon_id" : 3,
      "atlas_id" : null,
      "name" : "Urocissa erythroryncha magnirostris",
      "complete_species_count" : null,
      "default_photo" : null,
      "rank" : "subspecies",
      "ancestry" : "48460/1/2/355675/3/7251/7823/8413/495200",
      "rank_level" : 5,
      "taxon_schemes_count" : 1,
      "ancestor_ids" : [ 48460, 1, 2, 355675, 3, 7251, 7823, 8413, 495200, 495198 ],
      "id" : 495198,
      "parent_id" : 495200,
      "taxon_changes_count" : 0,
      "preferred_common_name" : null,
      "extinct" : null,
      "is_active" : true,
      "observations_count" : 0,
      "taxon_photos" : null,
      "conservation_statuses" : null,
      "children" : null,
      "ancestors" : null,
      "wikipedia_summary" : null
    }, {
      "min_species_ancestry" : null,
      "iconic_taxon_name" : "Aves",
      "created_at" : null,
      "iconic_taxon_id" : 3,
      "atlas_id" : null,
      "name" : "Urocissa erythroryncha occipitalis",
      "complete_species_count" : null,
      "default_photo" : null,
      "rank" : "subspecies",
      "ancestry" : "48460/1/2/355675/3/7251/7823/8413/495200",
      "rank_level" : 5,
      "taxon_schemes_count" : 1,
      "ancestor_ids" : [ 48460, 1, 2, 355675, 3, 7251, 7823, 8413, 495200, 495199 ],
      "id" : 495199,
      "parent_id" : 495200,
      "taxon_changes_count" : 0,
      "preferred_common_name" : null,
      "extinct" : null,
      "is_active" : true,
      "observations_count" : 0,
      "taxon_photos" : null,
      "conservation_statuses" : null,
      "children" : null,
      "ancestors" : null,
      "wikipedia_summary" : null
    } ],
    "ancestors" : [ {
      "min_species_ancestry" : null,
      "iconic_taxon_name" : "Animalia",
      "created_at" : null,
      "iconic_taxon_id" : 1,
      "atlas_id" : null,
      "name" : "Animalia",
      "complete_species_count" : null,
      "default_photo" : {
        "url" : "https://farm3.staticflickr.com/2188/2124709826_fd4ba36d1b_s.jpg",
        "license_code" : "cc-by-nc-nd",
        "type" : null,
        "attribution" : "(c) David Midgley, some rights reserved (CC BY-NC-ND)",
        "native_photo_id" : null,
        "small_url" : null,
        "medium_url" : "https://farm3.staticflickr.com/2188/2124709826_fd4ba36d1b.jpg",
        "large_url" : null,
        "square_url" : "https://farm3.staticflickr.com/2188/2124709826_fd4ba36d1b_s.jpg",
        "original_url" : null,
        "native_page_url" : null,
        "id" : 169,
        "flags" : [ ],
        "original_dimensions" : null
      },
      "rank" : "kingdom",
      "ancestry" : "48460",
      "rank_level" : 70,
      "taxon_schemes_count" : 2,
      "ancestor_ids" : [ 48460, 1 ],
      "id" : 1,
      "parent_id" : 48460,
      "taxon_changes_count" : 3,
      "preferred_common_name" : "Animals",
      "extinct" : false,
      "is_active" : true,
      "observations_count" : 4643456,
      "taxon_photos" : null,
      "conservation_statuses" : null,
      "children" : null,
      "ancestors" : null,
      "wikipedia_summary" : null
    }, {
      "min_species_ancestry" : null,
      "iconic_taxon_name" : "Animalia",
      "created_at" : null,
      "iconic_taxon_id" : 1,
      "atlas_id" : null,
      "name" : "Chordata",
      "complete_species_count" : null,
      "default_photo" : {
        "url" : "https://farm4.staticflickr.com/3272/2997294997_a68027cebb_s.jpg",
        "license_code" : "cc-by-nc-nd",
        "type" : null,
        "attribution" : "(c) Michael Gat, some rights reserved (CC BY-NC-ND)",
        "native_photo_id" : null,
        "small_url" : null,
        "medium_url" : "https://farm4.staticflickr.com/3272/2997294997_a68027cebb.jpg",
        "large_url" : null,
        "square_url" : "https://farm4.staticflickr.com/3272/2997294997_a68027cebb_s.jpg",
        "original_url" : null,
        "native_page_url" : null,
        "id" : 48283,
        "flags" : [ ],
        "original_dimensions" : null
      },
      "rank" : "phylum",
      "ancestry" : "48460/1",
      "rank_level" : 60,
      "taxon_schemes_count" : 2,
      "ancestor_ids" : [ 48460, 1, 2 ],
      "id" : 2,
      "parent_id" : 1,
      "taxon_changes_count" : 0,
      "preferred_common_name" : "Chordates",
      "extinct" : false,
      "is_active" : true,
      "observations_count" : 2420757,
      "taxon_photos" : null,
      "conservation_statuses" : null,
      "children" : null,
      "ancestors" : null,
      "wikipedia_summary" : null
    }, {
      "min_species_ancestry" : null,
      "iconic_taxon_name" : "Animalia",
      "created_at" : null,
      "iconic_taxon_id" : 1,
      "atlas_id" : null,
      "name" : "Vertebrata",
      "complete_species_count" : null,
      "default_photo" : {
        "url" : "https://farm8.staticflickr.com/7437/11571680965_69b3ee52b3_s.jpg",
        "license_code" : "cc-by-nc-sa",
        "type" : null,
        "attribution" : "(c) e_monk, some rights reserved (CC BY-NC-SA)",
        "native_photo_id" : null,
        "small_url" : null,
        "medium_url" : "https://farm8.staticflickr.com/7437/11571680965_69b3ee52b3.jpg",
        "large_url" : null,
        "square_url" : "https://farm8.staticflickr.com/7437/11571680965_69b3ee52b3_s.jpg",
        "original_url" : null,
        "native_page_url" : null,
        "id" : 11109049,
        "flags" : [ ],
        "original_dimensions" : null
      },
      "rank" : "subphylum",
      "ancestry" : "48460/1/2",
      "rank_level" : 57,
      "taxon_schemes_count" : 1,
      "ancestor_ids" : [ 48460, 1, 2, 355675 ],
      "id" : 355675,
      "parent_id" : 2,
      "taxon_changes_count" : 1,
      "preferred_common_name" : "Vertebrates",
      "extinct" : false,
      "is_active" : true,
      "observations_count" : 2417582,
      "taxon_photos" : null,
      "conservation_statuses" : null,
      "children" : null,
      "ancestors" : null,
      "wikipedia_summary" : null
    }, {
      "min_species_ancestry" : null,
      "iconic_taxon_name" : "Aves",
      "created_at" : null,
      "iconic_taxon_id" : 3,
      "atlas_id" : null,
      "name" : "Aves",
      "complete_species_count" : null,
      "default_photo" : {
        "url" : "https://farm1.staticflickr.com/205/499334547_68fab65c70_s.jpg",
        "license_code" : "cc-by-nc",
        "type" : null,
        "attribution" : "(c) Kenny P., some rights reserved (CC BY-NC)",
        "native_photo_id" : null,
        "small_url" : null,
        "medium_url" : "https://farm1.staticflickr.com/205/499334547_68fab65c70.jpg",
        "large_url" : null,
        "square_url" : "https://farm1.staticflickr.com/205/499334547_68fab65c70_s.jpg",
        "original_url" : null,
        "native_page_url" : null,
        "id" : 222,
        "flags" : [ ],
        "original_dimensions" : null
      },
      "rank" : "class",
      "ancestry" : "48460/1/2/355675",
      "rank_level" : 50,
      "taxon_schemes_count" : 2,
      "ancestor_ids" : [ 48460, 1, 2, 355675, 3 ],
      "id" : 3,
      "parent_id" : 355675,
      "taxon_changes_count" : 1,
      "preferred_common_name" : "Birds",
      "extinct" : false,
      "is_active" : true,
      "observations_count" : 1575037,
      "taxon_photos" : null,
      "conservation_statuses" : null,
      "children" : null,
      "ancestors" : null,
      "wikipedia_summary" : null
    }, {
      "min_species_ancestry" : null,
      "iconic_taxon_name" : "Aves",
      "created_at" : null,
      "iconic_taxon_id" : 3,
      "atlas_id" : null,
      "name" : "Passeriformes",
      "complete_species_count" : null,
      "default_photo" : {
        "url" : "https://media.eol.org/content/2012/06/15/20/32486_98_68.jpg",
        "license_code" : "cc-by",
        "type" : null,
        "attribution" : "(c) Mike Baird from Morro Bay, USA, some rights reserved (CC BY)",
        "native_photo_id" : null,
        "small_url" : null,
        "medium_url" : "https://media.eol.org/content/2012/06/15/20/32486_580_360.jpg",
        "large_url" : null,
        "square_url" : "https://media.eol.org/content/2012/06/15/20/32486_98_68.jpg",
        "original_url" : null,
        "native_page_url" : null,
        "id" : 3348552,
        "flags" : [ ],
        "original_dimensions" : null
      },
      "rank" : "order",
      "ancestry" : "48460/1/2/355675/3",
      "rank_level" : 40,
      "taxon_schemes_count" : 2,
      "ancestor_ids" : [ 48460, 1, 2, 355675, 3, 7251 ],
      "id" : 7251,
      "parent_id" : 3,
      "taxon_changes_count" : 0,
      "preferred_common_name" : "Perching Birds",
      "extinct" : false,
      "is_active" : true,
      "observations_count" : 701973,
      "taxon_photos" : null,
      "conservation_statuses" : null,
      "children" : null,
      "ancestors" : null,
      "wikipedia_summary" : null
    }, {
      "min_species_ancestry" : null,
      "iconic_taxon_name" : "Aves",
      "created_at" : null,
      "iconic_taxon_id" : 3,
      "atlas_id" : null,
      "name" : "Corvidae",
      "complete_species_count" : null,
      "default_photo" : {
        "url" : "https://static.inaturalist.org/photos/367335/square.jpg?1371023686",
        "license_code" : "cc-by-nc",
        "type" : null,
        "attribution" : "(c) smorsi, some rights reserved (CC BY-NC)",
        "native_photo_id" : null,
        "small_url" : null,
        "medium_url" : "https://static.inaturalist.org/photos/367335/medium.jpg?1371023686",
        "large_url" : null,
        "square_url" : "https://static.inaturalist.org/photos/367335/square.jpg?1371023686",
        "original_url" : null,
        "native_page_url" : null,
        "id" : 367335,
        "flags" : [ ],
        "original_dimensions" : {
          "width" : 425,
          "height" : 405
        }
      },
      "rank" : "family",
      "ancestry" : "48460/1/2/355675/3/7251",
      "rank_level" : 30,
      "taxon_schemes_count" : 1,
      "ancestor_ids" : [ 48460, 1, 2, 355675, 3, 7251, 7823 ],
      "id" : 7823,
      "parent_id" : 7251,
      "taxon_changes_count" : 0,
      "preferred_common_name" : "Crows, Jays, and Magpies",
      "extinct" : false,
      "is_active" : true,
      "observations_count" : 55436,
      "taxon_photos" : null,
      "conservation_statuses" : null,
      "children" : null,
      "ancestors" : null,
      "wikipedia_summary" : null
    }, {
      "min_species_ancestry" : null,
      "iconic_taxon_name" : "Aves",
      "created_at" : null,
      "iconic_taxon_id" : 3,
      "atlas_id" : null,
      "name" : "Urocissa",
      "complete_species_count" : null,
      "default_photo" : {
        "url" : "https://farm6.staticflickr.com/5296/5400624842_1be63e0eb1_s.jpg",
        "license_code" : "cc-by-nc-sa",
        "type" : null,
        "attribution" : "(c) Francesco Veronesi, some rights reserved (CC BY-NC-SA)",
        "native_photo_id" : null,
        "small_url" : null,
        "medium_url" : "https://farm6.staticflickr.com/5296/5400624842_1be63e0eb1.jpg",
        "large_url" : null,
        "square_url" : "https://farm6.staticflickr.com/5296/5400624842_1be63e0eb1_s.jpg",
        "original_url" : null,
        "native_page_url" : null,
        "id" : 66604,
        "flags" : [ ],
        "original_dimensions" : null
      },
      "rank" : "genus",
      "ancestry" : "48460/1/2/355675/3/7251/7823",
      "rank_level" : 20,
      "taxon_schemes_count" : 1,
      "ancestor_ids" : [ 48460, 1, 2, 355675, 3, 7251, 7823, 8413 ],
      "id" : 8413,
      "parent_id" : 7823,
      "taxon_changes_count" : 0,
      "preferred_common_name" : "Blue-Magpies",
      "extinct" : false,
      "is_active" : true,
      "observations_count" : 82,
      "taxon_photos" : null,
      "conservation_statuses" : null,
      "children" : null,
      "ancestors" : null,
      "wikipedia_summary" : null
    } ],
    "wikipedia_summary" : "The <b>red-billed blue magpie</b> (<i>Urocissa erythroryncha</i>) is a species of bird in the crow family, Corvidae. It is about the same size as the Eurasian magpie but has a much longer tail, one of the longest tails of any corvid. It is 65–68 cm (25.5–27 in) long and weighs 196–232 g (6.9–8.2 oz)."
  } ]
}