{
  "name" : null,
  "per_page" : 30,
  "page" : 1,
  "total_results" : 1,
  "results" : [ {
    "min_species_ancestry" : null,
    "iconic_taxon_name" : "Aves",
    "created_at" : null,
    "iconic_taxon_id" : 3,
    "atlas_id" : null,
    "name" : "Amazilia violiceps",
    "complete_species_count" : null,
    "default_photo" : {
      "url" : "https://farm4.staticflickr.com/3083/2752830435_c677bfaa03_s.jpg",
      "license_code" : "cc-by-nc-sa",
      "type" : null,
      "attribution" : "(c) Jerry Oldenettel, some rights reserved (CC BY-NC-SA)",
      "native_photo_id" : null,
      "small_url" : null,
      "medium_url" : "https://farm4.staticflickr.com/3083/2752830435_c677bfaa03.jpg",
      "large_url" : null,
      "square_url" : "https://farm4.staticflickr.com/3083/2752830435_c677bfaa03_s.jpg",
      "original_url" : null,
      "native_page_url" : null,
      "id" : 2703,
      "flags" : [ ],
      "original_dimensions" : null
    },
    "rank" : "species",
    "ancestry" : "48460/1/2/355675/3/67573/5562/5666",
    "rank_level" : 10,
    "taxon_schemes_count" : 9,
    "ancestor_ids" : [ 48460, 1, 2, 355675, 3, 67573, 5562, 5666 ],
    "id" : 5698,
    "parent_id" : 5666,
    "taxon_changes_count" : 0,
    "preferred_common_name" : "Violet-crowned Hummingbird",
    "extinct" : false,
    "is_active" : true,
    "observations_count" : 540,
    "taxon_photos" : [ {
      "photo" : {
        "url" : "https://farm4.staticflickr.com/3083/2752830435_c677bfaa03_s.jpg",
        "license_code" : "cc-by-nc-sa",
        "type" : "FlickrPhoto",
        "attribution" : "(c) Jerry Oldenettel, some rights reserved (CC BY-NC-SA)",
        "native_photo_id" : "2752830435",
        "small_url" : "https://farm4.staticflickr.com/3083/2752830435_c677bfaa03_m.jpg",
        "medium_url" : "https://farm4.staticflickr.com/3083/2752830435_c677bfaa03.jpg",
        "large_url" : "https://farm4.staticflickr.com/3083/2752830435_c677bfaa03_b.jpg",
        "square_url" : "https://farm4.staticflickr.com/3083/2752830435_c677bfaa03_s.jpg",
        "original_url" : "https://farm4.staticflickr.com/3083/2752830435_b46699b70e_o.jpg",
        "native_page_url" : "http://www.flickr.com/photos/7457894@N04/2752830435",
        "id" : 2703,
        "flags" : [ ],
        "original_dimensions" : null
      },
      "taxon" : {
        "min_species_ancestry" : "48460,1,2,355675,3,67573,5562,5666,5698",
        "iconic_taxon_name" : "Aves",
        "created_at" : "2008-03-13T02:49:02+00:00",
        "iconic_taxon_id" : 3,
        "atlas_id" : null,
        "name" : "Amazilia violiceps",
        "complete_species_count" : null,
        "default_photo" : {
          "url" : "https://farm4.staticflickr.com/3083/2752830435_c677bfaa03_s.jpg",
          "license_code" : "cc-by-nc-sa",
          "type" : null,
          "attribution" : "(c) Jerry Oldenettel, some rights reserved (CC BY-NC-SA)",
          "native_photo_id" : null,
          "small_url" : null,
          "medium_url" : "https://farm4.staticflickr.com/3083/2752830435_c677bfaa03.jpg",
          "large_url" : null,
          "square_url" : "https://farm4.staticflickr.com/3083/2752830435_c677bfaa03_s.jpg",
          "original_url" : null,
          "native_page_url" : null,
          "id" : 2703,
          "flags" : [ ],
          "original_dimensions" : null
        },
        "rank" : "species",
        "ancestry" : "48460/1/2/355675/3/67573/5562/5666",
        "rank_level" : 10,
        "taxon_schemes_count" : 9,
        "ancestor_ids" : [ 48460, 1, 2, 355675, 3, 67573, 5562, 5666, 5698 ],
        "id" : 5698,
        "parent_id" : 5666,
        "taxon_changes_count" : 0,
        "preferred_common_name" : "Violet-crowned Hummingbird",
        "extinct" : false,
        "is_active" : true,
        "observations_count" : 540,
        "taxon_photos" : null,
        "conservation_statuses" : null,
        "children" : null,
        "ancestors" : null,
        "wikipedia_summary" : null
      }
    }, {
      "photo" : {
        "url" : "https://static.inaturalist.org/photos/912185/square.jpg?1444572031",
        "license_code" : null,
        "type" : "LocalPhoto",
        "attribution" : "(c) Julio Alejandro Alvarez Ruiz, all rights reserved, uploaded by Julio Alejandro Álvarez Ruiz",
        "native_photo_id" : "14192734800",
        "small_url" : "https://static.inaturalist.org/photos/912185/small.jpg?1444572031",
        "medium_url" : "https://static.inaturalist.org/photos/912185/medium.jpg?1444572031",
        "large_url" : "https://static.inaturalist.org/photos/912185/large.jpg?1444572031",
        "square_url" : "https://static.inaturalist.org/photos/912185/square.jpg?1444572031",
        "original_url" : "https://static.inaturalist.org/photos/912185/original.jpg?1444572031",
        "native_page_url" : "https://www.flickr.com/photos/alvarezruiz/14192734800/",
        "id" : 912185,
        "flags" : [ ],
        "original_dimensions" : {
          "width" : 1968,
          "height" : 2048
        }
      },
      "taxon" : {
        "min_species_ancestry" : "48460,1,2,355675,3,67573,5562,5666,5698",
        "iconic_taxon_name" : "Aves",
        "created_at" : "2008-03-13T02:49:02+00:00",
        "iconic_taxon_id" : 3,
        "atlas_id" : null,
        "name" : "Amazilia violiceps",
        "complete_species_count" : null,
        "default_photo" : {
          "url" : "https://farm4.staticflickr.com/3083/2752830435_c677bfaa03_s.jpg",
          "license_code" : "cc-by-nc-sa",
          "type" : null,
          "attribution" : "(c) Jerry Oldenettel, some rights reserved (CC BY-NC-SA)",
          "native_photo_id" : null,
          "small_url" : null,
          "medium_url" : "https://farm4.staticflickr.com/3083/2752830435_c677bfaa03.jpg",
          "large_url" : null,
          "square_url" : "https://farm4.staticflickr.com/3083/2752830435_c677bfaa03_s.jpg",
          "original_url" : null,
          "native_page_url" : null,
          "id" : 2703,
          "flags" : [ ],
          "original_dimensions" : null
        },
        "rank" : "species",
        "ancestry" : "48460/1/2/355675/3/67573/5562/5666",
        "rank_level" : 10,
        "taxon_schemes_count" : 9,
        "ancestor_ids" : [ 48460, 1, 2, 355675, 3, 67573, 5562, 5666, 5698 ],
        "id" : 5698,
        "parent_id" : 5666,
        "taxon_changes_count" : 0,
        "preferred_common_name" : "Violet-crowned Hummingbird",
        "extinct" : false,
        "is_active" : true,
        "observations_count" : 540,
        "taxon_photos" : null,
        "conservation_statuses" : null,
        "children" : null,
        "ancestors" : null,
        "wikipedia_summary" : null
      }
    }, {
      "photo" : {
        "url" : "https://static.inaturalist.org/photos/575755/square.JPG?1384378541",
        "license_code" : "cc-by-nc",
        "type" : "LocalPhoto",
        "attribution" : "(c) Javier Salgado, some rights reserved (CC BY-NC)",
        "native_photo_id" : "575755",
        "small_url" : "https://static.inaturalist.org/photos/575755/small.JPG?1384378541",
        "medium_url" : "https://static.inaturalist.org/photos/575755/medium.JPG?1384378541",
        "large_url" : "https://static.inaturalist.org/photos/575755/large.JPG?1384378541",
        "square_url" : "https://static.inaturalist.org/photos/575755/square.JPG?1384378541",
        "original_url" : "https://static.inaturalist.org/photos/575755/original.JPG?1384378541",
        "native_page_url" : "https://www.inaturalist.org/photos/575755",
        "id" : 575755,
        "flags" : [ ],
        "original_dimensions" : {
          "width" : 2048,
          "height" : 1462
        }
      },
      "taxon" : {
        "min_species_ancestry" : "48460,1,2,355675,3,67573,5562,5666,5698",
        "iconic_taxon_name" : "Aves",
        "created_at" : "2008-03-13T02:49:02+00:00",
        "iconic_taxon_id" : 3,
        "atlas_id" : null,
        "name" : "Amazilia violiceps",
        "complete_species_count" : null,
        "default_photo" : {
          "url" : "https://farm4.staticflickr.com/3083/2752830435_c677bfaa03_s.jpg",
          "license_code" : "cc-by-nc-sa",
          "type" : null,
          "attribution" : "(c) Jerry Oldenettel, some rights reserved (CC BY-NC-SA)",
          "native_photo_id" : null,
          "small_url" : null,
          "medium_url" : "https://farm4.staticflickr.com/3083/2752830435_c677bfaa03.jpg",
          "large_url" : null,
          "square_url" : "https://farm4.staticflickr.com/3083/2752830435_c677bfaa03_s.jpg",
          "original_url" : null,
          "native_page_url" : null,
          "id" : 2703,
          "flags" : [ ],
          "original_dimensions" : null
        },
        "rank" : "species",
        "ancestry" : "48460/1/2/355675/3/67573/5562/5666",
        "rank_level" : 10,
        "taxon_schemes_count" : 9,
        "ancestor_ids" : [ 48460, 1, 2, 355675, 3, 67573, 5562, 5666, 5698 ],
        "id" : 5698,
        "parent_id" : 5666,
        "taxon_changes_count" : 0,
        "preferred_common_name" : "Violet-crowned Hummingbird",
        "extinct" : false,
        "is_active" : true,
        "observations_count" : 540,
        "taxon_photos" : null,
        "conservation_statuses" : null,
        "children" : null,
        "ancestors" : null,
        "wikipedia_summary" : null
      }
    }, {
      "photo" : {
        "url" : "https://static.inaturalist.org/photos/1425674/square.jpg?1444707824",
        "license_code" : null,
        "type" : "LocalPhoto",
        "attribution" : "(c) Julio Alejandro Alvarez Ruiz, all rights reserved, uploaded by Julio Alejandro Álvarez Ruiz",
        "native_photo_id" : "16029289522",
        "small_url" : "https://static.inaturalist.org/photos/1425674/small.jpg?1444707824",
        "medium_url" : "https://static.inaturalist.org/photos/1425674/medium.jpg?1444707824",
        "large_url" : "https://static.inaturalist.org/photos/1425674/large.jpg?1444707824",
        "square_url" : "https://static.inaturalist.org/photos/1425674/square.jpg?1444707824",
        "original_url" : "https://static.inaturalist.org/photos/1425674/original.jpg?1444707824",
        "native_page_url" : "https://www.flickr.com/photos/alvarezruiz/16029289522/",
        "id" : 1425674,
        "flags" : [ ],
        "original_dimensions" : {
          "width" : 2048,
          "height" : 1638
        }
      },
      "taxon" : {
        "min_species_ancestry" : "48460,1,2,355675,3,67573,5562,5666,5698",
        "iconic_taxon_name" : "Aves",
        "created_at" : "2008-03-13T02:49:02+00:00",
        "iconic_taxon_id" : 3,
        "atlas_id" : null,
        "name" : "Amazilia violiceps",
        "complete_species_count" : null,
        "default_photo" : {
          "url" : "https://farm4.staticflickr.com/3083/2752830435_c677bfaa03_s.jpg",
          "license_code" : "cc-by-nc-sa",
          "type" : null,
          "attribution" : "(c) Jerry Oldenettel, some rights reserved (CC BY-NC-SA)",
          "native_photo_id" : null,
          "small_url" : null,
          "medium_url" : "https://farm4.staticflickr.com/3083/2752830435_c677bfaa03.jpg",
          "large_url" : null,
          "square_url" : "https://farm4.staticflickr.com/3083/2752830435_c677bfaa03_s.jpg",
          "original_url" : null,
          "native_page_url" : null,
          "id" : 2703,
          "flags" : [ ],
          "original_dimensions" : null
        },
        "rank" : "species",
        "ancestry" : "48460/1/2/355675/3/67573/5562/5666",
        "rank_level" : 10,
        "taxon_schemes_count" : 9,
        "ancestor_ids" : [ 48460, 1, 2, 355675, 3, 67573, 5562, 5666, 5698 ],
        "id" : 5698,
        "parent_id" : 5666,
        "taxon_changes_count" : 0,
        "preferred_common_name" : "Violet-crowned Hummingbird",
        "extinct" : false,
        "is_active" : true,
        "observations_count" : 540,
        "taxon_photos" : null,
        "conservation_statuses" : null,
        "children" : null,
        "ancestors" : null,
        "wikipedia_summary" : null
      }
    }, {
      "photo" : {
        "url" : "https://static.inaturalist.org/photos/1425675/square.jpg?1444707829",
        "license_code" : null,
        "type" : "LocalPhoto",
        "attribution" : "(c) Julio Alejandro Alvarez Ruiz, all rights reserved, uploaded by Julio Alejandro Álvarez Ruiz",
        "native_photo_id" : "16029973305",
        "small_url" : "https://static.inaturalist.org/photos/1425675/small.jpg?1444707829",
        "medium_url" : "https://static.inaturalist.org/photos/1425675/medium.jpg?1444707829",
        "large_url" : "https://static.inaturalist.org/photos/1425675/large.jpg?1444707829",
        "square_url" : "https://static.inaturalist.org/photos/1425675/square.jpg?1444707829",
        "original_url" : "https://static.inaturalist.org/photos/1425675/original.jpg?1444707829",
        "native_page_url" : "https://www.flickr.com/photos/alvarezruiz/16029973305/",
        "id" : 1425675,
        "flags" : [ ],
        "original_dimensions" : {
          "width" : 2048,
          "height" : 1567
        }
      },
      "taxon" : {
        "min_species_ancestry" : "48460,1,2,355675,3,67573,5562,5666,5698",
        "iconic_taxon_name" : "Aves",
        "created_at" : "2008-03-13T02:49:02+00:00",
        "iconic_taxon_id" : 3,
        "atlas_id" : null,
        "name" : "Amazilia violiceps",
        "complete_species_count" : null,
        "default_photo" : {
          "url" : "https://farm4.staticflickr.com/3083/2752830435_c677bfaa03_s.jpg",
          "license_code" : "cc-by-nc-sa",
          "type" : null,
          "attribution" : "(c) Jerry Oldenettel, some rights reserved (CC BY-NC-SA)",
          "native_photo_id" : null,
          "small_url" : null,
          "medium_url" : "https://farm4.staticflickr.com/3083/2752830435_c677bfaa03.jpg",
          "large_url" : null,
          "square_url" : "https://farm4.staticflickr.com/3083/2752830435_c677bfaa03_s.jpg",
          "original_url" : null,
          "native_page_url" : null,
          "id" : 2703,
          "flags" : [ ],
          "original_dimensions" : null
        },
        "rank" : "species",
        "ancestry" : "48460/1/2/355675/3/67573/5562/5666",
        "rank_level" : 10,
        "taxon_schemes_count" : 9,
        "ancestor_ids" : [ 48460, 1, 2, 355675, 3, 67573, 5562, 5666, 5698 ],
        "id" : 5698,
        "parent_id" : 5666,
        "taxon_changes_count" : 0,
        "preferred_common_name" : "Violet-crowned Hummingbird",
        "extinct" : false,
        "is_active" : true,
        "observations_count" : 540,
        "taxon_photos" : null,
        "conservation_statuses" : null,
        "children" : null,
        "ancestors" : null,
        "wikipedia_summary" : null
      }
    }, {
      "photo" : {
        "url" : "https://static.inaturalist.org/photos/912186/square.jpg?1444572037",
        "license_code" : null,
        "type" : "LocalPhoto",
        "attribution" : "(c) Julio Alejandro Alvarez Ruiz, all rights reserved, uploaded by Julio Alejandro Álvarez Ruiz",
        "native_photo_id" : "14189496238",
        "small_url" : "https://static.inaturalist.org/photos/912186/small.jpg?1444572037",
        "medium_url" : "https://static.inaturalist.org/photos/912186/medium.jpg?1444572037",
        "large_url" : "https://static.inaturalist.org/photos/912186/large.jpg?1444572037",
        "square_url" : "https://static.inaturalist.org/photos/912186/square.jpg?1444572037",
        "original_url" : "https://static.inaturalist.org/photos/912186/original.jpg?1444572037",
        "native_page_url" : "https://www.flickr.com/photos/alvarezruiz/14189496238/",
        "id" : 912186,
        "flags" : [ ],
        "original_dimensions" : {
          "width" : 1817,
          "height" : 2048
        }
      },
      "taxon" : {
        "min_species_ancestry" : "48460,1,2,355675,3,67573,5562,5666,5698",
        "iconic_taxon_name" : "Aves",
        "created_at" : "2008-03-13T02:49:02+00:00",
        "iconic_taxon_id" : 3,
        "atlas_id" : null,
        "name" : "Amazilia violiceps",
        "complete_species_count" : null,
        "default_photo" : {
          "url" : "https://farm4.staticflickr.com/3083/2752830435_c677bfaa03_s.jpg",
          "license_code" : "cc-by-nc-sa",
          "type" : null,
          "attribution" : "(c) Jerry Oldenettel, some rights reserved (CC BY-NC-SA)",
          "native_photo_id" : null,
          "small_url" : null,
          "medium_url" : "https://farm4.staticflickr.com/3083/2752830435_c677bfaa03.jpg",
          "large_url" : null,
          "square_url" : "https://farm4.staticflickr.com/3083/2752830435_c677bfaa03_s.jpg",
          "original_url" : null,
          "native_page_url" : null,
          "id" : 2703,
          "flags" : [ ],
          "original_dimensions" : null
        },
        "rank" : "species",
        "ancestry" : "48460/1/2/355675/3/67573/5562/5666",
        "rank_level" : 10,
        "taxon_schemes_count" : 9,
        "ancestor_ids" : [ 48460, 1, 2, 355675, 3, 67573, 5562, 5666, 5698 ],
        "id" : 5698,
        "parent_id" : 5666,
        "taxon_changes_count" : 0,
        "preferred_common_name" : "Violet-crowned Hummingbird",
        "extinct" : false,
        "is_active" : true,
        "observations_count" : 540,
        "taxon_photos" : null,
        "conservation_statuses" : null,
        "children" : null,
        "ancestors" : null,
        "wikipedia_summary" : null
      }
    }, {
      "photo" : {
        "url" : "https://static.inaturalist.org/photos/5437166/square.jpg?1478347770",
        "license_code" : "cc-by-nc",
        "type" : "LocalPhoto",
        "attribution" : "(c) varajuan, some rights reserved (CC BY-NC), uploaded by Gordon Karre",
        "native_photo_id" : "5437166",
        "small_url" : "https://static.inaturalist.org/photos/5437166/small.jpg?1478347770",
        "medium_url" : "https://static.inaturalist.org/photos/5437166/medium.jpg?1478347770",
        "large_url" : "https://static.inaturalist.org/photos/5437166/large.jpg?1478347770",
        "square_url" : "https://static.inaturalist.org/photos/5437166/square.jpg?1478347770",
        "original_url" : "https://static.inaturalist.org/photos/5437166/original.jpg?1478347770",
        "native_page_url" : "https://www.inaturalist.org/photos/5437166",
        "id" : 5437166,
        "flags" : [ ],
        "original_dimensions" : {
          "width" : 1524,
          "height" : 1535
        }
      },
      "taxon" : {
        "min_species_ancestry" : "48460,1,2,355675,3,67573,5562,5666,5698",
        "iconic_taxon_name" : "Aves",
        "created_at" : "2008-03-13T02:49:02+00:00",
        "iconic_taxon_id" : 3,
        "atlas_id" : null,
        "name" : "Amazilia violiceps",
        "complete_species_count" : null,
        "default_photo" : {
          "url" : "https://farm4.staticflickr.com/3083/2752830435_c677bfaa03_s.jpg",
          "license_code" : "cc-by-nc-sa",
          "type" : null,
          "attribution" : "(c) Jerry Oldenettel, some rights reserved (CC BY-NC-SA)",
          "native_photo_id" : null,
          "small_url" : null,
          "medium_url" : "https://farm4.staticflickr.com/3083/2752830435_c677bfaa03.jpg",
          "large_url" : null,
          "square_url" : "https://farm4.staticflickr.com/3083/2752830435_c677bfaa03_s.jpg",
          "original_url" : null,
          "native_page_url" : null,
          "id" : 2703,
          "flags" : [ ],
          "original_dimensions" : null
        },
        "rank" : "species",
        "ancestry" : "48460/1/2/355675/3/67573/5562/5666",
        "rank_level" : 10,
        "taxon_schemes_count" : 9,
        "ancestor_ids" : [ 48460, 1, 2, 355675, 3, 67573, 5562, 5666, 5698 ],
        "id" : 5698,
        "parent_id" : 5666,
        "taxon_changes_count" : 0,
        "preferred_common_name" : "Violet-crowned Hummingbird",
        "extinct" : false,
        "is_active" : true,
        "observations_count" : 540,
        "taxon_photos" : null,
        "conservation_statuses" : null,
        "children" : null,
        "ancestors" : null,
        "wikipedia_summary" : null
      }
    }, {
      "photo" : {
        "url" : "https://static.inaturalist.org/photos/5436985/square.jpg?1478343512",
        "license_code" : "cc-by-nc",
        "type" : "LocalPhoto",
        "attribution" : "(c) varajuan, some rights reserved (CC BY-NC), uploaded by Gordon Karre",
        "native_photo_id" : "5436985",
        "small_url" : "https://static.inaturalist.org/photos/5436985/small.jpg?1478343512",
        "medium_url" : "https://static.inaturalist.org/photos/5436985/medium.jpg?1478343512",
        "large_url" : "https://static.inaturalist.org/photos/5436985/large.jpg?1478343512",
        "square_url" : "https://static.inaturalist.org/photos/5436985/square.jpg?1478343512",
        "original_url" : "https://static.inaturalist.org/photos/5436985/original.jpg?1478343512",
        "native_page_url" : "https://www.inaturalist.org/photos/5436985",
        "id" : 5436985,
        "flags" : [ ],
        "original_dimensions" : {
          "width" : 1512,
          "height" : 1649
        }
      },
      "taxon" : {
        "min_species_ancestry" : "48460,1,2,355675,3,67573,5562,5666,5698",
        "iconic_taxon_name" : "Aves",
        "created_at" : "2008-03-13T02:49:02+00:00",
        "iconic_taxon_id" : 3,
        "atlas_id" : null,
        "name" : "Amazilia violiceps",
        "complete_species_count" : null,
        "default_photo" : {
          "url" : "https://farm4.staticflickr.com/3083/2752830435_c677bfaa03_s.jpg",
          "license_code" : "cc-by-nc-sa",
          "type" : null,
          "attribution" : "(c) Jerry Oldenettel, some rights reserved (CC BY-NC-SA)",
          "native_photo_id" : null,
          "small_url" : null,
          "medium_url" : "https://farm4.staticflickr.com/3083/2752830435_c677bfaa03.jpg",
          "large_url" : null,
          "square_url" : "https://farm4.staticflickr.com/3083/2752830435_c677bfaa03_s.jpg",
          "original_url" : null,
          "native_page_url" : null,
          "id" : 2703,
          "flags" : [ ],
          "original_dimensions" : null
        },
        "rank" : "species",
        "ancestry" : "48460/1/2/355675/3/67573/5562/5666",
        "rank_level" : 10,
        "taxon_schemes_count" : 9,
        "ancestor_ids" : [ 48460, 1, 2, 355675, 3, 67573, 5562, 5666, 5698 ],
        "id" : 5698,
        "parent_id" : 5666,
        "taxon_changes_count" : 0,
        "preferred_common_name" : "Violet-crowned Hummingbird",
        "extinct" : false,
        "is_active" : true,
        "observations_count" : 540,
        "taxon_photos" : null,
        "conservation_statuses" : null,
        "children" : null,
        "ancestors" : null,
        "wikipedia_summary" : null
      }
    }, {
      "photo" : {
        "url" : "https://static.inaturalist.org/photos/5281041/square.jpg?1476965399",
        "license_code" : "cc-by-nc",
        "type" : "LocalPhoto",
        "attribution" : "(c) Brian Hinds, some rights reserved (CC BY-NC)",
        "native_photo_id" : "5281041",
        "small_url" : "https://static.inaturalist.org/photos/5281041/small.jpg?1476965399",
        "medium_url" : "https://static.inaturalist.org/photos/5281041/medium.jpg?1476965399",
        "large_url" : "https://static.inaturalist.org/photos/5281041/large.jpg?1476965399",
        "square_url" : "https://static.inaturalist.org/photos/5281041/square.jpg?1476965399",
        "original_url" : "https://static.inaturalist.org/photos/5281041/original.jpg?1476965399",
        "native_page_url" : "https://www.inaturalist.org/photos/5281041",
        "id" : 5281041,
        "flags" : [ ],
        "original_dimensions" : {
          "width" : 1802,
          "height" : 2048
        }
      },
      "taxon" : {
        "min_species_ancestry" : "48460,1,2,355675,3,67573,5562,5666,5698",
        "iconic_taxon_name" : "Aves",
        "created_at" : "2008-03-13T02:49:02+00:00",
        "iconic_taxon_id" : 3,
        "atlas_id" : null,
        "name" : "Amazilia violiceps",
        "complete_species_count" : null,
        "default_photo" : {
          "url" : "https://farm4.staticflickr.com/3083/2752830435_c677bfaa03_s.jpg",
          "license_code" : "cc-by-nc-sa",
          "type" : null,
          "attribution" : "(c) Jerry Oldenettel, some rights reserved (CC BY-NC-SA)",
          "native_photo_id" : null,
          "small_url" : null,
          "medium_url" : "https://farm4.staticflickr.com/3083/2752830435_c677bfaa03.jpg",
          "large_url" : null,
          "square_url" : "https://farm4.staticflickr.com/3083/2752830435_c677bfaa03_s.jpg",
          "original_url" : null,
          "native_page_url" : null,
          "id" : 2703,
          "flags" : [ ],
          "original_dimensions" : null
        },
        "rank" : "species",
        "ancestry" : "48460/1/2/355675/3/67573/5562/5666",
        "rank_level" : 10,
        "taxon_schemes_count" : 9,
        "ancestor_ids" : [ 48460, 1, 2, 355675, 3, 67573, 5562, 5666, 5698 ],
        "id" : 5698,
        "parent_id" : 5666,
        "taxon_changes_count" : 0,
        "preferred_common_name" : "Violet-crowned Hummingbird",
        "extinct" : false,
        "is_active" : true,
        "observations_count" : 540,
        "taxon_photos" : null,
        "conservation_statuses" : null,
        "children" : null,
        "ancestors" : null,
        "wikipedia_summary" : null
      }
    }, {
      "photo" : {
        "url" : "https://static.inaturalist.org/photos/5352189/square.jpeg?1477555995",
        "license_code" : null,
        "type" : "LocalPhoto",
        "attribution" : "(c) Julio Alejandro Álvarez Ruiz, all rights reserved",
        "native_photo_id" : "5352189",
        "small_url" : "https://static.inaturalist.org/photos/5352189/small.jpeg?1477555995",
        "medium_url" : "https://static.inaturalist.org/photos/5352189/medium.jpeg?1477555995",
        "large_url" : "https://static.inaturalist.org/photos/5352189/large.jpeg?1477555995",
        "square_url" : "https://static.inaturalist.org/photos/5352189/square.jpeg?1477555995",
        "original_url" : "https://static.inaturalist.org/photos/5352189/original.jpeg?1477555995",
        "native_page_url" : "http://conabio.inaturalist.org/photos/5352189",
        "id" : 5352189,
        "flags" : [ ],
        "original_dimensions" : {
          "width" : 716,
          "height" : 800
        }
      },
      "taxon" : {
        "min_species_ancestry" : "48460,1,2,355675,3,67573,5562,5666,5698",
        "iconic_taxon_name" : "Aves",
        "created_at" : "2008-03-13T02:49:02+00:00",
        "iconic_taxon_id" : 3,
        "atlas_id" : null,
        "name" : "Amazilia violiceps",
        "complete_species_count" : null,
        "default_photo" : {
          "url" : "https://farm4.staticflickr.com/3083/2752830435_c677bfaa03_s.jpg",
          "license_code" : "cc-by-nc-sa",
          "type" : null,
          "attribution" : "(c) Jerry Oldenettel, some rights reserved (CC BY-NC-SA)",
          "native_photo_id" : null,
          "small_url" : null,
          "medium_url" : "https://farm4.staticflickr.com/3083/2752830435_c677bfaa03.jpg",
          "large_url" : null,
          "square_url" : "https://farm4.staticflickr.com/3083/2752830435_c677bfaa03_s.jpg",
          "original_url" : null,
          "native_page_url" : null,
          "id" : 2703,
          "flags" : [ ],
          "original_dimensions" : null
        },
        "rank" : "species",
        "ancestry" : "48460/1/2/355675/3/67573/5562/5666",
        "rank_level" : 10,
        "taxon_schemes_count" : 9,
        "ancestor_ids" : [ 48460, 1, 2, 355675, 3, 67573, 5562, 5666, 5698 ],
        "id" : 5698,
        "parent_id" : 5666,
        "taxon_changes_count" : 0,
        "preferred_common_name" : "Violet-crowned Hummingbird",
        "extinct" : false,
        "is_active" : true,
        "observations_count" : 540,
        "taxon_photos" : null,
        "conservation_statuses" : null,
        "children" : null,
        "ancestors" : null,
        "wikipedia_summary" : null
      }
    } ],
    "conservation_statuses" : [ {
      "description" : null,
      "iucn" : 10,
      "url" : "http://www.iucnredlist.org/details/106001958",
      "authority" : "IUCN Red List",
      "taxon_id" : 5698,
      "place" : null,
      "status" : "LC"
    } ],
    "children" : null,
    "ancestors" : [ {
      "min_species_ancestry" : null,
      "iconic_taxon_name" : "Animalia",
      "created_at" : null,
      "iconic_taxon_id" : 1,
      "atlas_id" : null,
      "name" : "Animalia",
      "complete_species_count" : null,
      "default_photo" : {
        "url" : "https://farm3.staticflickr.com/2188/2124709826_fd4ba36d1b_s.jpg",
        "license_code" : "cc-by-nc-nd",
        "type" : null,
        "attribution" : "(c) David Midgley, some rights reserved (CC BY-NC-ND)",
        "native_photo_id" : null,
        "small_url" : null,
        "medium_url" : "https://farm3.staticflickr.com/2188/2124709826_fd4ba36d1b.jpg",
        "large_url" : null,
        "square_url" : "https://farm3.staticflickr.com/2188/2124709826_fd4ba36d1b_s.jpg",
        "original_url" : null,
        "native_page_url" : null,
        "id" : 169,
        "flags" : [ ],
        "original_dimensions" : null
      },
      "rank" : "kingdom",
      "ancestry" : "48460",
      "rank_level" : 70,
      "taxon_schemes_count" : 2,
      "ancestor_ids" : [ 48460, 1 ],
      "id" : 1,
      "parent_id" : 48460,
      "taxon_changes_count" : 3,
      "preferred_common_name" : "Animals",
      "extinct" : false,
      "is_active" : true,
      "observations_count" : 4643669,
      "taxon_photos" : null,
      "conservation_statuses" : null,
      "children" : null,
      "ancestors" : null,
      "wikipedia_summary" : null
    }, {
      "min_species_ancestry" : null,
      "iconic_taxon_name" : "Animalia",
      "created_at" : null,
      "iconic_taxon_id" : 1,
      "atlas_id" : null,
      "name" : "Chordata",
      "complete_species_count" : null,
      "default_photo" : {
        "url" : "https://farm4.staticflickr.com/3272/2997294997_a68027cebb_s.jpg",
        "license_code" : "cc-by-nc-nd",
        "type" : null,
        "attribution" : "(c) Michael Gat, some rights reserved (CC BY-NC-ND)",
        "native_photo_id" : null,
        "small_url" : null,
        "medium_url" : "https://farm4.staticflickr.com/3272/2997294997_a68027cebb.jpg",
        "large_url" : null,
        "square_url" : "https://farm4.staticflickr.com/3272/2997294997_a68027cebb_s.jpg",
        "original_url" : null,
        "native_page_url" : null,
        "id" : 48283,
        "flags" : [ ],
        "original_dimensions" : null
      },
      "rank" : "phylum",
      "ancestry" : "48460/1",
      "rank_level" : 60,
      "taxon_schemes_count" : 2,
      "ancestor_ids" : [ 48460, 1, 2 ],
      "id" : 2,
      "parent_id" : 1,
      "taxon_changes_count" : 0,
      "preferred_common_name" : "Chordates",
      "extinct" : false,
      "is_active" : true,
      "observations_count" : 2420883,
      "taxon_photos" : null,
      "conservation_statuses" : null,
      "children" : null,
      "ancestors" : null,
      "wikipedia_summary" : null
    }, {
      "min_species_ancestry" : null,
      "iconic_taxon_name" : "Animalia",
      "created_at" : null,
      "iconic_taxon_id" : 1,
      "atlas_id" : null,
      "name" : "Vertebrata",
      "complete_species_count" : null,
      "default_photo" : {
        "url" : "https://farm8.staticflickr.com/7437/11571680965_69b3ee52b3_s.jpg",
        "license_code" : "cc-by-nc-sa",
        "type" : null,
        "attribution" : "(c) e_monk, some rights reserved (CC BY-NC-SA)",
        "native_photo_id" : null,
        "small_url" : null,
        "medium_url" : "https://farm8.staticflickr.com/7437/11571680965_69b3ee52b3.jpg",
        "large_url" : null,
        "square_url" : "https://farm8.staticflickr.com/7437/11571680965_69b3ee52b3_s.jpg",
        "original_url" : null,
        "native_page_url" : null,
        "id" : 11109049,
        "flags" : [ ],
        "original_dimensions" : null
      },
      "rank" : "subphylum",
      "ancestry" : "48460/1/2",
      "rank_level" : 57,
      "taxon_schemes_count" : 1,
      "ancestor_ids" : [ 48460, 1, 2, 355675 ],
      "id" : 355675,
      "parent_id" : 2,
      "taxon_changes_count" : 1,
      "preferred_common_name" : "Vertebrates",
      "extinct" : false,
      "is_active" : true,
      "observations_count" : 2417702,
      "taxon_photos" : null,
      "conservation_statuses" : null,
      "children" : null,
      "ancestors" : null,
      "wikipedia_summary" : null
    }, {
      "min_species_ancestry" : null,
      "iconic_taxon_name" : "Aves",
      "created_at" : null,
      "iconic_taxon_id" : 3,
      "atlas_id" : null,
      "name" : "Aves",
      "complete_species_count" : null,
      "default_photo" : {
        "url" : "https://farm1.staticflickr.com/205/499334547_68fab65c70_s.jpg",
        "license_code" : "cc-by-nc",
        "type" : null,
        "attribution" : "(c) Kenny P., some rights reserved (CC BY-NC)",
        "native_photo_id" : null,
        "small_url" : null,
        "medium_url" : "https://farm1.staticflickr.com/205/499334547_68fab65c70.jpg",
        "large_url" : null,
        "square_url" : "https://farm1.staticflickr.com/205/499334547_68fab65c70_s.jpg",
        "original_url" : null,
        "native_page_url" : null,
        "id" : 222,
        "flags" : [ ],
        "original_dimensions" : null
      },
      "rank" : "class",
      "ancestry" : "48460/1/2/355675",
      "rank_level" : 50,
      "taxon_schemes_count" : 2,
      "ancestor_ids" : [ 48460, 1, 2, 355675, 3 ],
      "id" : 3,
      "parent_id" : 355675,
      "taxon_changes_count" : 1,
      "preferred_common_name" : "Birds",
      "extinct" : false,
      "is_active" : true,
      "observations_count" : 1575116,
      "taxon_photos" : null,
      "conservation_statuses" : null,
      "children" : null,
      "ancestors" : null,
      "wikipedia_summary" : null
    }, {
      "min_species_ancestry" : null,
      "iconic_taxon_name" : "Aves",
      "created_at" : null,
      "iconic_taxon_id" : 3,
      "atlas_id" : null,
      "name" : "Caprimulgiformes",
      "complete_species_count" : null,
      "default_photo" : {
        "url" : "https://farm3.staticflickr.com/2679/4148484836_2b6b67d06b_s.jpg",
        "license_code" : "cc-by-nc-nd",
        "type" : null,
        "attribution" : "(c) Carol Vinzant, some rights reserved (CC BY-NC-ND)",
        "native_photo_id" : null,
        "small_url" : null,
        "medium_url" : "https://farm3.staticflickr.com/2679/4148484836_2b6b67d06b.jpg",
        "large_url" : null,
        "square_url" : "https://farm3.staticflickr.com/2679/4148484836_2b6b67d06b_s.jpg",
        "original_url" : null,
        "native_page_url" : null,
        "id" : 98626,
        "flags" : [ ],
        "original_dimensions" : null
      },
      "rank" : "order",
      "ancestry" : "48460/1/2/355675/3",
      "rank_level" : 40,
      "taxon_schemes_count" : 1,
      "ancestor_ids" : [ 48460, 1, 2, 355675, 3, 67573 ],
      "id" : 67573,
      "parent_id" : 3,
      "taxon_changes_count" : 1,
      "preferred_common_name" : "Nightjars, Swifts, Hummingbirds, and Allies",
      "extinct" : false,
      "is_active" : true,
      "observations_count" : 35592,
      "taxon_photos" : null,
      "conservation_statuses" : null,
      "children" : null,
      "ancestors" : null,
      "wikipedia_summary" : null
    }, {
      "min_species_ancestry" : null,
      "iconic_taxon_name" : "Aves",
      "created_at" : null,
      "iconic_taxon_id" : 3,
      "atlas_id" : null,
      "name" : "Trochilidae",
      "complete_species_count" : null,
      "default_photo" : {
        "url" : "https://farm4.staticflickr.com/3439/3788145771_8468cee58d_s.jpg",
        "license_code" : "cc-by-nc-nd",
        "type" : null,
        "attribution" : "(c) Anders Illum, some rights reserved (CC BY-NC-ND)",
        "native_photo_id" : null,
        "small_url" : null,
        "medium_url" : "https://farm4.staticflickr.com/3439/3788145771_8468cee58d.jpg",
        "large_url" : null,
        "square_url" : "https://farm4.staticflickr.com/3439/3788145771_8468cee58d_s.jpg",
        "original_url" : null,
        "native_page_url" : null,
        "id" : 6222,
        "flags" : [ ],
        "original_dimensions" : null
      },
      "rank" : "family",
      "ancestry" : "48460/1/2/355675/3/67573",
      "rank_level" : 30,
      "taxon_schemes_count" : 2,
      "ancestor_ids" : [ 48460, 1, 2, 355675, 3, 67573, 5562 ],
      "id" : 5562,
      "parent_id" : 67573,
      "taxon_changes_count" : 0,
      "preferred_common_name" : "Hummingbirds",
      "extinct" : false,
      "is_active" : true,
      "observations_count" : 28736,
      "taxon_photos" : null,
      "conservation_statuses" : null,
      "children" : null,
      "ancestors" : null,
      "wikipedia_summary" : null
    }, {
      "min_species_ancestry" : null,
      "iconic_taxon_name" : "Aves",
      "created_at" : null,
      "iconic_taxon_id" : 3,
      "atlas_id" : null,
      "name" : "Amazilia",
      "complete_species_count" : null,
      "default_photo" : {
        "url" : "https://farm4.staticflickr.com/3631/3418143848_76a81972cf_s.jpg",
        "license_code" : "cc-by-nc-sa",
        "type" : null,
        "attribution" : "(c) Jerry Oldenettel, some rights reserved (CC BY-NC-SA)",
        "native_photo_id" : null,
        "small_url" : null,
        "medium_url" : "https://farm4.staticflickr.com/3631/3418143848_76a81972cf.jpg",
        "large_url" : null,
        "square_url" : "https://farm4.staticflickr.com/3631/3418143848_76a81972cf_s.jpg",
        "original_url" : null,
        "native_page_url" : null,
        "id" : 17492,
        "flags" : [ ],
        "original_dimensions" : null
      },
      "rank" : "genus",
      "ancestry" : "48460/1/2/355675/3/67573/5562",
      "rank_level" : 20,
      "taxon_schemes_count" : 1,
      "ancestor_ids" : [ 48460, 1, 2, 355675, 3, 67573, 5562, 5666 ],
      "id" : 5666,
      "parent_id" : 5562,
      "taxon_changes_count" : 0,
      "preferred_common_name" : null,
      "extinct" : false,
      "is_active" : true,
      "observations_count" : 2933,
      "taxon_photos" : null,
      "conservation_statuses" : null,
      "children" : null,
      "ancestors" : null,
      "wikipedia_summary" : null
    } ],
    "wikipedia_summary" : "The <b>Violet-crowned Hummingbird</b> (<i>Amazilia violiceps</i>) is a medium-sized hummingbird. It is 10 cm long and weighs approximately 5 g."
  } ]
}